{"type":"FeatureCollection",
"name":"Arbre_bat_T",
"crs":{"type":"name","properties":{"name":"urn:ogc:def:crs:OGC:1.3:CRS84"}},
"features":[
    {"type":"Feature","properties":{},"geometry":{"coordinates":[-1.702534691811593,48.118942648481635],"type":"Point"}}]}